subseasonal_data/__init__.py
subseasonal_data/data_loaders.py
subseasonal_data/downloader.py
subseasonal_data/utils.py
subseasonal_data-0.1.0.dist-info/LICENSE
subseasonal_data-0.1.0.dist-info/METADATA
subseasonal_data-0.1.0.dist-info/WHEEL
subseasonal_data-0.1.0.dist-info/top_level.txt
subseasonal_data-0.1.0.dist-info/RECORD
