Metadata-Version: 2.1
Name: subseasonal_data
Version: 0.1.0
Summary: Data access package for the SubseasonalClimateUSA dataset.
Home-page: https://github.com/microsoft/subseasonal_data
License-File: LICENSE
Requires-Dist: numpy
Requires-Dist: pandas
Requires-Dist: scikit-learn
Requires-Dist: netCDF4
